odoo/addons/product_product_template_link/README.rst
odoo/addons/product_product_template_link/__init__.py
odoo/addons/product_product_template_link/__manifest__.py
odoo/addons/product_product_template_link/i18n/ca.po
odoo/addons/product_product_template_link/i18n/es.po
odoo/addons/product_product_template_link/i18n/it.po
odoo/addons/product_product_template_link/i18n/product_product_template_link.pot
odoo/addons/product_product_template_link/i18n/product_product_template_navigation.pot
odoo/addons/product_product_template_link/models/__init__.py
odoo/addons/product_product_template_link/models/product_product.py
odoo/addons/product_product_template_link/readme/CONTRIBUTORS.md
odoo/addons/product_product_template_link/readme/DESCRIPTION.md
odoo/addons/product_product_template_link/static/description/icon.png
odoo/addons/product_product_template_link/static/description/index.html
odoo/addons/product_product_template_link/static/img/template_navigation.gif
odoo/addons/product_product_template_link/tests/__init__.py
odoo/addons/product_product_template_link/tests/test_product_product_template_link.py
odoo/addons/product_product_template_link/views/product_product_views.xml
odoo_addon_product_product_template_link-18.0.1.0.0.2.dist-info/METADATA
odoo_addon_product_product_template_link-18.0.1.0.0.2.dist-info/WHEEL
odoo_addon_product_product_template_link-18.0.1.0.0.2.dist-info/top_level.txt
odoo_addon_product_product_template_link-18.0.1.0.0.2.dist-info/RECORD
